setup.py
hermes_pygments/__init__.py
hermes_pygments/hermes_lexer.py
hermes_pygments.egg-info/PKG-INFO
hermes_pygments.egg-info/SOURCES.txt
hermes_pygments.egg-info/dependency_links.txt
hermes_pygments.egg-info/entry_points.txt
hermes_pygments.egg-info/requires.txt
hermes_pygments.egg-info/top_level.txt