Metadata-Version: 1.0
Name: hermes-pygments
Version: 0.1
Summary: Pygments for Hermes grammar files, abstract syntax trees, and parse trees
Home-page: UNKNOWN
Author: Scott Frazer
Author-email: scott.d.frazer@gmail.com
License: UNKNOWN
Platform: UNKNOWN
